MANIFEST.in
README.md
pyproject.toml
setup.py
cpp/qNoise.cpp
cpp/qNoise.h
qnoise/__init__.py
qnoise/qNoisePy.cpp
qnoise.egg-info/PKG-INFO
qnoise.egg-info/SOURCES.txt
qnoise.egg-info/dependency_links.txt
qnoise.egg-info/not-zip-safe
qnoise.egg-info/requires.txt
qnoise.egg-info/top_level.txt