Metadata-Version: 2.4
Name: qnoise
Version: 1.0.1
Summary: Non-Gaussian colored noise generator
Author-email: "J. Ignacio Deza" <ignacio.deza@uwe.ac.uk>
License-Expression: MIT
Project-URL: Homepage, https://github.com/ignaciodeza/qNoise
Project-URL: Repository, https://github.com/ignaciodeza/qNoise
Project-URL: Paper, https://doi.org/10.1016/j.softx.2022.101034
Keywords: noise,stochastic,non-gaussian,colored-noise
Classifier: Development Status :: 5 - Production/Stable
Classifier: Intended Audience :: Science/Research
Classifier: Programming Language :: Python :: 3
Classifier: Programming Language :: Python :: 3.8
Classifier: Programming Language :: Python :: 3.9
Classifier: Programming Language :: Python :: 3.10
Classifier: Programming Language :: Python :: 3.11
Classifier: Programming Language :: Python :: 3.12
Requires-Python: >=3.8
Requires-Dist: numpy>=1.20.0
